gdrive2/__init__.py
gdrive2/auth_util.py
gdrive2/drive_util.py
gdrive2/gd
gdrive2/gd.py
gdrive2/paths.py
gdrive2-0.7.0.dist-info/LICENSE
gdrive2-0.7.0.dist-info/METADATA
gdrive2-0.7.0.dist-info/WHEEL
gdrive2-0.7.0.dist-info/top_level.txt
gdrive2-0.7.0.dist-info/RECORD
