Metadata-Version: 2.1
Name: gdrive2
Version: 0.7.0
Summary: File management tools for Google Drive based on PyDrive
Home-page: https://github.com/preethampaul/gdrive2
Author: Preetham Paul
Author-email: preeth@uw.edu
License: UNKNOWN
Project-URL: Documentation, https://gdrive2.readthedocs.io
Platform: UNKNOWN
Classifier: Programming Language :: Python :: 3
Classifier: License :: OSI Approved :: MIT License
Classifier: Operating System :: OS Independent
Requires-Python: >=3
Requires-Dist: PyDrive (>=1.3.1)
